exhub/_version.py
exhub/application.py
exhub/flags.py
exhub/ioc.py
exhub/motor.py
exhub_ioc-0.1.0.dist-info/METADATA
exhub_ioc-0.1.0.dist-info/WHEEL
exhub_ioc-0.1.0.dist-info/entry_points.txt
exhub_ioc-0.1.0.dist-info/top_level.txt
exhub_ioc-0.1.0.dist-info/RECORD
