Metadata-Version: 2.1
Name: exhub-ioc
Version: 0.1.0
Summary: CAproto-based pure-Python EPICS IOC for the Huber SMC 9300 motor controller
Author-email: Florin Boariu <florin.pt@rootshell.ro>
Classifier: Programming Language :: Python :: 3
Classifier: License :: OSI Approved :: GNU General Public License v3 or later (GPLv3+)
Classifier: Operating System :: POSIX :: Linux
Classifier: Development Status :: 2 - Pre-Alpha
Classifier: Environment :: Console
Classifier: Intended Audience :: Science/Research
Classifier: Topic :: Scientific/Engineering
Requires-Python: >=3.8
Requires-Dist: caproto
Requires-Dist: emmi >=0.1.4
Requires-Dist: schema
Requires-Dist: parse
Requires-Dist: pyvisa-py
Provides-Extra: test
Requires-Dist: pytest ; extra == 'test'
Requires-Dist: pytest-cov ; extra == 'test'
Requires-Dist: pytest-asyncio ; extra == 'test'
